micropython_mmc5603/__init__.py
micropython_mmc5603/i2c_helpers.py
micropython_mmc5603/mmc5603.py
micropython_mmc5603-0.1.0.dist-info/LICENSE
micropython_mmc5603-0.1.0.dist-info/METADATA
micropython_mmc5603-0.1.0.dist-info/WHEEL
micropython_mmc5603-0.1.0.dist-info/top_level.txt
micropython_mmc5603-0.1.0.dist-info/RECORD
