Metadata-Version: 2.1
Name: micropython-mmc5603
Version: 0.1.0
Summary: MicroPython driver for the Memsic MMC5603 Magnetometer
Author-email: JDM <xxyx@mailmeto.mozmail.com>
License: MIT
Project-URL: Homepage, https://github.com/jposada202020/MicroPython_MMC5603
Keywords: sensor,micropython,mmc5603,micropython,driver,sensor,memsic,mmc5603,magnetometer
Classifier: Intended Audience :: Developers
Classifier: Topic :: Software Development :: Libraries
Classifier: Topic :: Software Development :: Embedded Systems
Classifier: Topic :: System :: Hardware
Classifier: License :: OSI Approved :: MIT License
Classifier: Programming Language :: Python :: Implementation :: MicroPython
License-File: LICENSE
